MANIFEST.in
README.rst
setup.cfg
setup.py
django_templatetags_bundle.egg-info/PKG-INFO
django_templatetags_bundle.egg-info/SOURCES.txt
django_templatetags_bundle.egg-info/dependency_links.txt
django_templatetags_bundle.egg-info/not-zip-safe
django_templatetags_bundle.egg-info/requires.txt
django_templatetags_bundle.egg-info/top_level.txt
templatetags_bundle/__init__.py
templatetags_bundle/version.py
templatetags_bundle/templatetags/__init__.py
templatetags_bundle/templatetags/bundle.py